{
  "ROOT": {
    "type": { "resolvedName": "Background" },
    "isCanvas": true,
    "props": {
      "rows": 10,
      "columns": 11,
      "lockedGrid": false,
      "backgroundColor": "#292929",
      "layout": [
        { "i": "0", "x": 1, "y": 1, "w": 5, "h": 1 },
        { "i": "1", "x": 1, "y": 2, "w": 2, "h": 6 },
        { "i": "2", "x": 3, "y": 2, "w": 7, "h": 4 },
        { "i": "3", "x": 3, "y": 6, "w": 7, "h": 2 },
        { "i": "4", "x": 1, "y": 9, "w": 10, "h": 1 }
      ]
    },
    "displayName": "Background",
    "custom": {},
    "parent": null,
    "hidden": false,
    "nodes": [],
    "linkedNodes": {
      "0": "NavigationBarGridCell",
      "1": "SidePanelGridCell",
      "2": "MainContentGridCell",
      "3": "PossibleOptionsGridCell",
      "4": "FooterGridCell"
    }
  },
  "NavigationBarGridCell": {
    "type": { "resolvedName": "GridCell" },
    "isCanvas": true,
    "props": {
      "flexDirection": "row",
      "justifyContent": "center",
      "alignItems": "center",
      "gap": 10
    },
    "displayName": "GridCell",
    "custom": { "id": "0" },
    "parent": "ROOT",
    "hidden": false,
    "nodes": ["NavigationBarContainer"],
    "linkedNodes": {}
  },
  "NavigationBarContainer": {
    "type": { "resolvedName": "Container" },
    "isCanvas": true,
    "props": {
      "height": 100,
      "width": 100,
      "flexDirection": "row",
      "justifyContent": "space-around",
      "alignItems": "center",
      "gap": 10,
      "backgroundColor": "ghostwhite",
      "borderRadius": 5,
      "borderColor": "black",
      "padding": 0,
      "shadowColor": "black",
      "shadowOffsetX": 1,
      "shadowOffsetY": 1,
      "shadowBlur": 3
    },
    "displayName": "Container",
    "custom": {},
    "parent": "NavigationBarGridCell",
    "hidden": false,
    "nodes": [
      "NavigationBarButton0",
      "NavigationBarButton1",
      "NavigationBarButton2",
      "NavigationBarButton3"
    ],
    "linkedNodes": {}
  },
  "NavigationBarButton0": {
    "type": { "resolvedName": "Button" },
    "isCanvas": false,
    "props": {
      "backgroundColor": "lightslategrey",
      "fontSize": 16,
      "fontColor": "white",
      "borderRadius": 4,
      "width": 20,
      "height": 80,
      "text": "Home",
      "alignment": "center",
      "displayName": "Button",
      "bordercolor": "white",
      "shadowColor": "black",
      "shadowOffsetX": 1,
      "shadowOffsetY": 1,
      "shadowBlur": 3
    },
    "displayName": "Button",
    "custom": {},
    "parent": "NavigationBarContainer",
    "hidden": false,
    "nodes": [],
    "linkedNodes": {}
  },
  "NavigationBarButton1": {
    "type": { "resolvedName": "Button" },
    "isCanvas": false,
    "props": {
      "backgroundColor": "lightslategrey",
      "fontSize": 16,
      "fontColor": "white",
      "borderRadius": 4,
      "width": 20,
      "height": 80,
      "text": "Tab 1",
      "alignment": "center",
      "displayName": "Button",
      "bordercolor": "white",
      "shadowColor": "black",
      "shadowOffsetX": 1,
      "shadowOffsetY": 1,
      "shadowBlur": 3
    },
    "displayName": "Button",
    "custom": {},
    "parent": "NavigationBarContainer",
    "hidden": false,
    "nodes": [],
    "linkedNodes": {}
  },
  "NavigationBarButton2": {
    "type": { "resolvedName": "Button" },
    "isCanvas": false,
    "props": {
      "backgroundColor": "lightslategrey",
      "fontSize": 16,
      "fontColor": "white",
      "borderRadius": 4,
      "width": 20,
      "height": 80,
      "text": "Tab 2",
      "alignment": "center",
      "displayName": "Button",
      "bordercolor": "white",
      "shadowColor": "black",
      "shadowOffsetX": 1,
      "shadowOffsetY": 1,
      "shadowBlur": 3
    },
    "displayName": "Button",
    "custom": {},
    "parent": "NavigationBarContainer",
    "hidden": false,
    "nodes": [],
    "linkedNodes": {}
  },
  "NavigationBarButton3": {
    "type": { "resolvedName": "Button" },
    "isCanvas": false,
    "props": {
      "backgroundColor": "lightslategrey",
      "fontSize": 16,
      "fontColor": "white",
      "borderRadius": 4,
      "width": 20,
      "height": 80,
      "text": "Tab 3",
      "alignment": "center",
      "displayName": "Button",
      "bordercolor": "white",
      "shadowColor": "black",
      "shadowOffsetX": 1,
      "shadowOffsetY": 1,
      "shadowBlur": 3
    },
    "displayName": "Button",
    "custom": {},
    "parent": "NavigationBarContainer",
    "hidden": false,
    "nodes": [],
    "linkedNodes": {}
  },
  "SidePanelGridCell": {
    "type": { "resolvedName": "GridCell" },
    "isCanvas": true,
    "props": {
      "flexDirection": "row",
      "justifyContent": "center",
      "alignItems": "center",
      "gap": 10
    },
    "displayName": "GridCell",
    "custom": { "id": "1" },
    "parent": "ROOT",
    "hidden": false,
    "nodes": ["SidePanelContainer"],
    "linkedNodes": {}
  },
  "SidePanelContainer": {
    "type": { "resolvedName": "Container" },
    "isCanvas": true,
    "props": {
      "height": 100,
      "width": 100,
      "flexDirection": "column",
      "justifyContent": "space-around",
      "alignItems": "center",
      "gap": 10,
      "backgroundColor": "ghostwhite",
      "borderRadius": 5,
      "borderColor": "black",
      "padding": 0,
      "shadowColor": "black",
      "shadowOffsetX": 1,
      "shadowOffsetY": 1,
      "shadowBlur": 3
    },
    "displayName": "Container",
    "custom": {},
    "parent": "SidePanelGridCell",
    "hidden": false,
    "nodes": [
      "SidePanelButton0",
      "SidePanelButton1",
      "SidePanelButton2",
      "SidePanelButton3",
      "SidePanelButton4"
    ],
    "linkedNodes": {}
  },
  "SidePanelButton0": {
    "type": { "resolvedName": "Button" },
    "isCanvas": false,
    "props": {
      "backgroundColor": "lightslategrey",
      "fontSize": 16,
      "fontColor": "white",
      "borderRadius": 4,
      "width": 80,
      "height": 15,
      "text": "Option 1",
      "alignment": "center",
      "displayName": "Button",
      "bordercolor": "white",
      "shadowColor": "black",
      "shadowOffsetX": 1,
      "shadowOffsetY": 1,
      "shadowBlur": 3
    },
    "displayName": "Button",
    "custom": {},
    "parent": "SidePanelContainer",
    "hidden": false,
    "nodes": [],
    "linkedNodes": {}
  },
  "SidePanelButton1": {
    "type": { "resolvedName": "Button" },
    "isCanvas": false,
    "props": {
      "backgroundColor": "lightslategrey",
      "fontSize": 16,
      "fontColor": "white",
      "borderRadius": 4,
      "width": 80,
      "height": 15,
      "text": "Option 2",
      "alignment": "center",
      "displayName": "Button",
      "bordercolor": "white",
      "shadowColor": "black",
      "shadowOffsetX": 1,
      "shadowOffsetY": 1,
      "shadowBlur": 3
    },
    "displayName": "Button",
    "custom": {},
    "parent": "SidePanelContainer",
    "hidden": false,
    "nodes": [],
    "linkedNodes": {}
  },
  "SidePanelButton2": {
    "type": { "resolvedName": "Button" },
    "isCanvas": false,
    "props": {
      "backgroundColor": "lightslategrey",
      "fontSize": 16,
      "fontColor": "white",
      "borderRadius": 4,
      "width": 80,
      "height": 15,
      "text": "Option 3",
      "alignment": "center",
      "displayName": "Button",
      "bordercolor": "white",
      "shadowColor": "black",
      "shadowOffsetX": 1,
      "shadowOffsetY": 1,
      "shadowBlur": 3
    },
    "displayName": "Button",
    "custom": {},
    "parent": "SidePanelContainer",
    "hidden": false,
    "nodes": [],
    "linkedNodes": {}
  },
  "SidePanelButton3": {
    "type": { "resolvedName": "Button" },
    "isCanvas": false,
    "props": {
      "backgroundColor": "lightslategrey",
      "fontSize": 16,
      "fontColor": "white",
      "borderRadius": 4,
      "width": 80,
      "height": 15,
      "text": "Option 4",
      "alignment": "center",
      "displayName": "Button",
      "bordercolor": "white",
      "shadowColor": "black",
      "shadowOffsetX": 1,
      "shadowOffsetY": 1,
      "shadowBlur": 3
    },
    "displayName": "Button",
    "custom": {},
    "parent": "SidePanelContainer",
    "hidden": false,
    "nodes": [],
    "linkedNodes": {}
  },
  "SidePanelButton4": {
    "type": { "resolvedName": "Button" },
    "isCanvas": false,
    "props": {
      "backgroundColor": "lightslategrey",
      "fontSize": 16,
      "fontColor": "white",
      "borderRadius": 4,
      "width": 80,
      "height": 15,
      "text": "Option 5",
      "alignment": "center",
      "displayName": "Button",
      "bordercolor": "white",
      "shadowColor": "black",
      "shadowOffsetX": 1,
      "shadowOffsetY": 1,
      "shadowBlur": 3
    },
    "displayName": "Button",
    "custom": {},
    "parent": "SidePanelContainer",
    "hidden": false,
    "nodes": [],
    "linkedNodes": {}
  },
  "MainContentGridCell": {
    "type": { "resolvedName": "GridCell" },
    "isCanvas": true,
    "props": {
      "flexDirection": "row",
      "justifyContent": "center",
      "alignItems": "center",
      "gap": 10
    },
    "displayName": "GridCell",
    "custom": { "id": "2" },
    "parent": "ROOT",
    "hidden": false,
    "nodes": ["MainContentContainer"],
    "linkedNodes": {}
  },
  "MainContentContainer": {
    "type": { "resolvedName": "Container" },
    "isCanvas": true,
    "props": {
      "height": 100,
      "width": 100,
      "flexDirection": "column",
      "justifyContent": "space-around",
      "alignItems": "center",
      "gap": 10,
      "backgroundColor": "ghostwhite",
      "borderRadius": 5,
      "borderColor": "black",
      "padding": 0,
      "shadowColor": "black",
      "shadowOffsetX": 1,
      "shadowOffsetY": 1,
      "shadowBlur": 3
    },
    "displayName": "Container",
    "custom": {},
    "parent": "MainContentGridCell",
    "hidden": false,
    "nodes": ["MainContentLabel0", "MainContentImage1"],
    "linkedNodes": {}
  },
  "MainContentLabel0": {
    "type": { "resolvedName": "Label" },
    "isCanvas": false,
    "props": {
      "text": "STEP 1",
      "fontSize": 22,
      "fontColor": "black",
      "userEditable": true,
      "textAlign": "left",
      "icon": "none",
      "hyperlink": "",
      "bold": true,
      "italic": false,
      "underline": false
    },
    "displayName": "Label",
    "custom": {},
    "parent": "MainContentContainer",
    "hidden": false,
    "nodes": [],
    "linkedNodes": {}
  },
  "MainContentImage1": {
    "type": { "resolvedName": "Image" },
    "isCanvas": false,
    "props": {
      "src": "https://photographylife.com/wp-content/uploads/2023/05/Nikon-Z8-Official-Samples-00002.jpg",
      "alt": "Placeholder",
      "width": 100,
      "height": 80
    },
    "displayName": "Image",
    "custom": {},
    "parent": "MainContentContainer",
    "hidden": false,
    "nodes": [],
    "linkedNodes": {}
  },
  "PossibleOptionsGridCell": {
    "type": { "resolvedName": "GridCell" },
    "isCanvas": true,
    "props": {
      "flexDirection": "row",
      "justifyContent": "center",
      "alignItems": "center",
      "gap": 10
    },
    "displayName": "GridCell",
    "custom": { "id": "3" },
    "parent": "ROOT",
    "hidden": false,
    "nodes": ["PossibleOptionsContainer"],
    "linkedNodes": {}
  },
  "PossibleOptionsContainer": {
    "type": { "resolvedName": "Container" },
    "isCanvas": true,
    "props": {
      "height": 100,
      "width": 100,
      "flexDirection": "column",
      "justifyContent": "space-around",
      "alignItems": "center",
      "gap": 10,
      "backgroundColor": "ghostwhite",
      "borderRadius": 5,
      "borderColor": "black",
      "padding": 0,
      "shadowColor": "black",
      "shadowOffsetX": 1,
      "shadowOffsetY": 1,
      "shadowBlur": 3
    },
    "displayName": "Container",
    "custom": {},
    "parent": "PossibleOptionsGridCell",
    "hidden": false,
    "nodes": ["PossibleOptionsLabel0", "PossibleOptionsInput1"],
    "linkedNodes": {}
  },
  "PossibleOptionsLabel0": {
    "type": { "resolvedName": "Label" },
    "isCanvas": false,
    "props": {
      "text": "POSSIBLE",
      "fontSize": 22,
      "fontColor": "black",
      "userEditable": true,
      "textAlign": "left",
      "icon": "none",
      "hyperlink": "",
      "bold": true,
      "italic": false,
      "underline": false
    },
    "displayName": "Label",
    "custom": {},
    "parent": "PossibleOptionsContainer",
    "hidden": false,
    "nodes": [],
    "linkedNodes": {}
  },
  "PossibleOptionsInput1": {
    "type": { "resolvedName": "Input" },
    "isCanvas": false,
    "props": {
      "fontSize": 14,
      "fontColor": "black",
      "backgroundColor": "white",
      "placeholder": "Select an option",
      "borderRadius": 4
    },
    "displayName": "Input",
    "custom": {},
    "parent": "PossibleOptionsContainer",
    "hidden": false,
    "nodes": [],
    "linkedNodes": {}
  },
  "FooterGridCell": {
    "type": { "resolvedName": "GridCell" },
    "isCanvas": true,
    "props": {
      "flexDirection": "row",
      "justifyContent": "center",
      "alignItems": "center",
      "gap": 10
    },
    "displayName": "GridCell",
    "custom": { "id": "4" },
    "parent": "ROOT",
    "hidden": false,
    "nodes": ["FooterContainer"],
    "linkedNodes": {}
  },
  "FooterContainer": {
    "type": { "resolvedName": "Container" },
    "isCanvas": true,
    "props": {
      "height": 100,
      "width": 100,
      "flexDirection": "row",
      "justifyContent": "space-around",
      "alignItems": "center",
      "gap": 10,
      "backgroundColor": "ghostwhite",
      "borderRadius": 5,
      "borderColor": "black",
      "padding": 0,
      "shadowColor": "black",
      "shadowOffsetX": 1,
      "shadowOffsetY": 1,
      "shadowBlur": 3
    },
    "displayName": "Container",
    "custom": {},
    "parent": "FooterGridCell",
    "hidden": false,
    "nodes": ["FooterInput0", "FooterTextBox1"],
    "linkedNodes": {}
  },
  "FooterInput0": {
    "type": { "resolvedName": "Input" },
    "isCanvas": false,
    "props": {
      "fontSize": 14,
      "fontColor": "black",
      "backgroundColor": "white",
      "placeholder": "Search",
      "borderRadius": 4
    },
    "displayName": "Input",
    "custom": {},
    "parent": "FooterContainer",
    "hidden": false,
    "nodes": [],
    "linkedNodes": {}
  },
  "FooterTextBox1": {
    "type": { "resolvedName": "TextBox" },
    "isCanvas": false,
    "props": {
      "text": "Contact Area",
      "fontSize": 14,
      "fontColor": "black",
      "backgroundColor": "white",
      "placeholder": "Enter text",
      "borderRadius": 4,
      "height": 60,
      "width": 50,
      "alignment": "left"
    },
    "displayName": "TextBox",
    "custom": {},
    "parent": "FooterContainer",
    "hidden": false,
    "nodes": [],
    "linkedNodes": {}
  }
}
