{
  "ROOT": {
    "type": { "resolvedName": "Background" },
    "isCanvas": true,
    "props": {
      "rows": 9,
      "columns": 11,
      "lockedGrid": false,
      "backgroundColor": "#292929",
      "layout": [
        { "i": "0", "x": 1, "y": 1, "w": 10, "h": 1 },
        { "i": "1", "x": 1, "y": 2, "w": 3, "h": 6 },
        { "i": "2", "x": 4, "y": 2, "w": 6, "h": 6 },
        { "i": "3", "x": 1, "y": 8, "w": 10, "h": 1 }
      ]
    },
    "displayName": "Background",
    "custom": {},
    "parent": null,
    "hidden": false,
    "nodes": [],
    "linkedNodes": {
      "0": "headerGridCell",
      "1": "mainLeftGridCell",
      "2": "mainRightGridCell",
      "3": "footerGridCell"
    }
  },
  "headerGridCell": {
    "type": { "resolvedName": "GridCell" },
    "isCanvas": true,
    "props": {
      "flexDirection": "row",
      "justifyContent": "space-between",
      "alignItems": "center",
      "gap": 10
    },
    "displayName": "GridCell",
    "custom": { "id": "0" },
    "parent": "ROOT",
    "hidden": false,
    "nodes": ["headerContainer"],
    "linkedNodes": {}
  },
  "headerContainer": {
    "type": { "resolvedName": "Container" },
    "isCanvas": true,
    "props": {
      "height": 100,
      "width": 100,
      "flexDirection": "row",
      "gap": 10,
      "backgroundColor": "E8F8FF",
      "borderRadius": 4,
      "borderColor": "black",
      "padding": 10,
      "shadowColor": "transparent",
      "shadowOffsetX": 2,
      "shadowOffsetY": 2,
      "shadowBlur": 2
    },
    "displayName": "Container",
    "custom": {},
    "parent": "headerGridCell",
    "hidden": false,
    "nodes": ["Home", "Button1", "Button2", "Button3"],
    "linkedNodes": {}
  },
  "Home": {
    "type": { "resolvedName": "Button" },
    "isCanvas": false,
    "props": {
      "backgroundColor": "466673",
      "fontSize": 14,
      "fontColor": "black",
      "borderRadius": 4,
      "width": 80,
      "height": 60,
      "text": "Home",
      "alignment": "center"
    },
    "displayName": "Button",
    "custom": {},
    "parent": "headerContainer",
    "hidden": false,
    "nodes": [],
    "linkedNodes": {}
  },
  "Button1": {
    "type": { "resolvedName": "Button" },
    "isCanvas": false,
    "props": {
      "backgroundColor": "466673",
      "fontSize": 14,
      "fontColor": "black",
      "borderRadius": 4,
      "width": 80,
      "height": 60,
      "text": "Button",
      "alignment": "center"
    },
    "displayName": "Button",
    "custom": {},
    "parent": "headerContainer",
    "hidden": false,
    "nodes": [],
    "linkedNodes": {}
  },
  "Button2": {
    "type": { "resolvedName": "Button" },
    "isCanvas": false,
    "props": {
      "backgroundColor": "466673",
      "fontSize": 14,
      "fontColor": "black",
      "borderRadius": 4,
      "width": 80,
      "height": 60,
      "text": "Button",
      "alignment": "center"
    },
    "displayName": "Button",
    "custom": {},
    "parent": "headerContainer",
    "hidden": false,
    "nodes": [],
    "linkedNodes": {}
  },
  "Button3": {
    "type": { "resolvedName": "Button" },
    "isCanvas": false,
    "props": {
      "backgroundColor": "466673",
      "fontSize": 14,
      "fontColor": "black",
      "borderRadius": 4,
      "width": 80,
      "height": 60,
      "text": "Button",
      "alignment": "center"
    },
    "displayName": "Button",
    "custom": {},
    "parent": "headerContainer",
    "hidden": false,
    "nodes": [],
    "linkedNodes": {}
  },
  "mainLeftGridCell": {
    "type": { "resolvedName": "GridCell" },
    "isCanvas": true,
    "props": {
      "flexDirection": "row",
      "justifyContent": "space-between",
      "alignItems": "center",
      "gap": 10
    },
    "displayName": "GridCell",
    "custom": { "id": "1" },
    "parent": "ROOT",
    "hidden": false,
    "nodes": ["mainLeftContainer"],
    "linkedNodes": {}
  },
  "mainLeftContainer": {
    "type": { "resolvedName": "Container" },
    "isCanvas": true,
    "props": {
      "height": 100,
      "width": 100,
      "flexDirection": "column",
      "gap": 10,
      "backgroundColor": "FEF9EF",
      "borderRadius": 4,
      "borderColor": "black",
      "padding": 10,
      "shadowColor": "transparent",
      "shadowOffsetX": 2,
      "shadowOffsetY": 2,
      "shadowBlur": 2
    },
    "displayName": "Container",
    "custom": {},
    "parent": "mainLeftGridCell",
    "hidden": false,
    "nodes": ["Label1", "Label2", "Label3", "Label4"],
    "linkedNodes": {}
  },
  "Label1": {
    "type": { "resolvedName": "Label" },
    "isCanvas": false,
    "props": { "text": "Label", "fontSize": 14, "fontcolor": "black", "textAlign": "left" },
    "displayName": "Label",
    "custom": {},
    "parent": "mainLeftContainer",
    "hidden": false,
    "nodes": [],
    "linkedNodes": {}
  },
  "Label2": {
    "type": { "resolvedName": "Label" },
    "isCanvas": false,
    "props": { "text": "Label", "fontSize": 14, "fontcolor": "black", "textAlign": "left" },
    "displayName": "Label",
    "custom": {},
    "parent": "mainLeftContainer",
    "hidden": false,
    "nodes": [],
    "linkedNodes": {}
  },
  "Label3": {
    "type": { "resolvedName": "Label" },
    "isCanvas": false,
    "props": { "text": "Label", "fontSize": 14, "fontcolor": "black", "textAlign": "left" },
    "displayName": "Label",
    "custom": {},
    "parent": "mainLeftContainer",
    "hidden": false,
    "nodes": [],
    "linkedNodes": {}
  },
  "Label4": {
    "type": { "resolvedName": "Label" },
    "isCanvas": false,
    "props": { "text": "Label", "fontSize": 14, "fontcolor": "black", "textAlign": "left" },
    "displayName": "Label",
    "custom": {},
    "parent": "mainLeftContainer",
    "hidden": false,
    "nodes": [],
    "linkedNodes": {}
  },
  "mainRightGridCell": {
    "type": { "resolvedName": "GridCell" },
    "isCanvas": true,
    "props": {
      "flexDirection": "row",
      "justifyContent": "space-between",
      "alignItems": "center",
      "gap": 10
    },
    "displayName": "GridCell",
    "custom": { "id": "2" },
    "parent": "ROOT",
    "hidden": false,
    "nodes": ["mainRightContainer"],
    "linkedNodes": {}
  },
  "mainRightContainer": {
    "type": { "resolvedName": "Container" },
    "isCanvas": true,
    "props": {
      "height": 100,
      "width": 100,
      "flexDirection": "column",
      "gap": 10,
      "backgroundColor": "FEF9EF",
      "borderRadius": 4,
      "borderColor": "black",
      "padding": 10,
      "shadowColor": "transparent",
      "shadowOffsetX": 2,
      "shadowOffsetY": 2,
      "shadowBlur": 2
    },
    "displayName": "Container",
    "custom": {},
    "parent": "mainRightGridCell",
    "hidden": false,
    "nodes": ["StepLabel", "MainImage", "Textbox", "Possible"],
    "linkedNodes": {}
  },
  "StepLabel": {
    "type": { "resolvedName": "Label" },
    "isCanvas": false,
    "props": { "text": "Step 1", "fontSize": 14, "fontcolor": "black", "textAlign": "left" },
    "displayName": "Label",
    "custom": {},
    "parent": "mainRightContainer",
    "hidden": false,
    "nodes": [],
    "linkedNodes": {}
  },
  "MainImage": {
    "type": { "resolvedName": "Image" },
    "isCanvas": false,
    "props": {
      "src": "https://via.placeholder.com/150",
      "alt": "Image",
      "width": 150,
      "height": 150
    },
    "displayName": "Image",
    "custom": {},
    "parent": "mainRightContainer",
    "hidden": false,
    "nodes": [],
    "linkedNodes": {}
  },
  "Textbox": {
    "type": { "resolvedName": "TextBox" },
    "isCanvas": false,
    "props": {
      "text": "Text Box",
      "fontSize": 14,
      "fontColor": "black",
      "backgroundColor": "466673",
      "placeholder": "Enter text",
      "borderRadius": 4,
      "height": 100,
      "width": 100,
      "alignment": "left"
    },
    "displayName": "TextBox",
    "custom": {},
    "parent": "mainRightContainer",
    "hidden": false,
    "nodes": [],
    "linkedNodes": {}
  },
  "Possible": {
    "type": { "resolvedName": "Input" },
    "isCanvas": false,
    "props": {
      "fontSize": 14,
      "fontColor": "black",
      "backgroundColor": "466673",
      "placeholder": "Enter text",
      "borderRadius": 4
    },
    "displayName": "Input",
    "custom": {},
    "parent": "mainRightContainer",
    "hidden": false,
    "nodes": [],
    "linkedNodes": {}
  },
  "footerGridCell": {
    "type": { "resolvedName": "GridCell" },
    "isCanvas": true,
    "props": {
      "flexDirection": "row",
      "justifyContent": "space-between",
      "alignItems": "center",
      "gap": 10
    },
    "displayName": "GridCell",
    "custom": { "id": "3" },
    "parent": "ROOT",
    "hidden": false,
    "nodes": ["footerContainer"],
    "linkedNodes": {}
  },
  "footerContainer": {
    "type": { "resolvedName": "Container" },
    "isCanvas": true,
    "props": {
      "height": 100,
      "width": 100,
      "flexDirection": "row",
      "gap": 10,
      "backgroundColor": "E8F8FF",
      "borderRadius": 4,
      "borderColor": "black",
      "padding": 10,
      "shadowColor": "transparent",
      "shadowOffsetX": 2,
      "shadowOffsetY": 2,
      "shadowBlur": 2
    },
    "displayName": "Container",
    "custom": {},
    "parent": "footerGridCell",
    "hidden": false,
    "nodes": ["SearchButton", "Icon1", "Icon2", "Icon3", "Contact"],
    "linkedNodes": {}
  },
  "SearchButton": {
    "type": { "resolvedName": "Button" },
    "isCanvas": false,
    "props": {
      "backgroundColor": "466673",
      "fontSize": 14,
      "fontColor": "black",
      "borderRadius": 4,
      "width": 80,
      "height": 60,
      "text": "Search",
      "alignment": "center"
    },
    "displayName": "Button",
    "custom": {},
    "parent": "footerContainer",
    "hidden": false,
    "nodes": [],
    "linkedNodes": {}
  },
  "Icon1": {
    "type": { "resolvedName": "Icon" },
    "isCanvas": false,
    "props": {},
    "displayName": "Icon",
    "custom": {},
    "parent": "footerContainer",
    "hidden": false,
    "nodes": [],
    "linkedNodes": {}
  },
  "Icon2": {
    "type": { "resolvedName": "Icon" },
    "isCanvas": false,
    "props": {},
    "displayName": "Icon",
    "custom": {},
    "parent": "footerContainer",
    "hidden": false,
    "nodes": [],
    "linkedNodes": {}
  },
  "Icon3": {
    "type": { "resolvedName": "Icon" },
    "isCanvas": false,
    "props": {},
    "displayName": "Icon",
    "custom": {},
    "parent": "footerContainer",
    "hidden": false,
    "nodes": [],
    "linkedNodes": {}
  },
  "Contact": {
    "type": { "resolvedName": "Label" },
    "isCanvas": false,
    "props": { "text": "Contact", "fontSize": 14, "fontcolor": "black", "textAlign": "left" },
    "displayName": "Label",
    "custom": {},
    "parent": "footerContainer",
    "hidden": false,
    "nodes": [],
    "linkedNodes": {}
  }
}
