[
  {
    "section": "Header",
    "children": [
      { "type": "Button", "props": { "width": 8, "height": 8, "text": "Home", "icon": "VscHome" } },
      { "type": "Button", "props": { "width": 8, "height": 8, "text": "Nav1", "icon": "VscInfo" } },
      { "type": "Button", "props": { "width": 8, "height": 8, "text": "Nav2", "icon": "VscInfo" } },
      { "type": "Button", "props": { "width": 8, "height": 8, "text": "Nav3", "icon": "VscInfo" } },
      { "type": "Button", "props": { "width": 8, "height": 8, "text": "Nav4", "icon": "VscInfo" } }
    ]
  },
  {
    "section": "Sidebar",
    "children": [
      {
        "type": "Button",
        "props": { "width": 8, "height": 8, "text": "Menu1", "icon": "VscSettingsGear" }
      },
      {
        "type": "Button",
        "props": { "width": 8, "height": 8, "text": "Menu2", "icon": "VscSettingsGear" }
      },
      {
        "type": "Button",
        "props": { "width": 8, "height": 8, "text": "Menu3", "icon": "VscSettingsGear" }
      },
      {
        "type": "Button",
        "props": { "width": 8, "height": 8, "text": "Menu4", "icon": "VscSettingsGear" }
      },
      {
        "type": "Button",
        "props": { "width": 8, "height": 8, "text": "Menu5", "icon": "VscSettingsGear" }
      }
    ]
  },
  {
    "section": "Main",
    "children": [
      {
        "type": "Label",
        "props": { "text": "Step 1", "bold": true, "italic": false, "underline": false }
      },
      {
        "type": "Image",
        "props": {
          "src": "https://via.placeholder.com/150",
          "alt": "Main Placeholder",
          "width": 85,
          "height": 45
        }
      },
      { "type": "Text", "props": { "text": "Additional content line 1" } },
      { "type": "Text", "props": { "text": "Additional content line 2" } },
      { "type": "Text", "props": { "text": "Additional content line 3" } }
    ]
  },
  {
    "section": "Subsection",
    "children": [
      {
        "type": "Label",
        "props": { "text": "Possible", "bold": true, "italic": false, "underline": false }
      },
      {
        "type": "Input",
        "props": { "backgroundColor": "Main", "placeholder": "Select an option" }
      },
      { "type": "Text", "props": { "text": "Further information below the dropdown" } }
    ]
  },
  {
    "section": "Footer",
    "children": [
      { "type": "Input", "props": { "backgroundColor": "Main", "placeholder": "Search" } },
      {
        "type": "Icon",
        "props": { "selectedIcon": "VscSearch", "iconSize": 18, "iconColor": "Main" }
      },
      {
        "type": "Icon",
        "props": { "selectedIcon": "VscAdd", "iconSize": 18, "iconColor": "Main" }
      },
      {
        "type": "Icon",
        "props": { "selectedIcon": "VscSave", "iconSize": 18, "iconColor": "Main" }
      },
      {
        "type": "Label",
        "props": { "text": "Contact", "bold": true, "italic": false, "underline": false }
      },
      { "type": "Text", "props": { "text": "1234 Main St" } },
      { "type": "Text", "props": { "text": "City, ST 12345" } },
      { "type": "Text", "props": { "text": "Email: contact@example.com" } }
    ]
  }
]
