{
  "ROOT": {
    "type": { "resolvedName": "Background" },
    "isCanvas": true,
    "props": {
      "rows": 10,
      "columns": 11,
      "lockedGrid": false,
      "backgroundColor": "292929",
      "layout": [
        { "i": "0", "x": 1, "y": 1, "w": 10, "h": 1 },
        { "i": "1", "x": 1, "y": 2, "w": 3, "h": 6 },
        { "i": "2", "x": 4, "y": 2, "w": 6, "h": 6 },
        { "i": "3", "x": 1, "y": 8, "w": 10, "h": 2 }
      ]
    },
    "displayName": "Background",
    "custom": {},
    "parent": null,
    "hidden": false,
    "nodes": [],
    "linkedNodes": {
      "0": "navigationbarGridCell",
      "1": "leftsidebarGridCell",
      "2": "maincontentGridCell",
      "3": "footerGridCell"
    }
  },
  "navigationbarGridCell": {
    "type": { "resolvedName": "GridCell" },
    "isCanvas": true,
    "props": {
      "flexDirection": "row",
      "justifyContent": "center",
      "alignItems": "center",
      "gap": 10
    },
    "displayName": "GridCell",
    "custom": { "id": "0" },
    "parent": "ROOT",
    "hidden": false,
    "nodes": ["navigationbarContainer"],
    "linkedNodes": {}
  },
  "navigationbarContainer": {
    "type": { "resolvedName": "Container" },
    "isCanvas": true,
    "props": {
      "height": 100,
      "width": 100,
      "flexDirection": "row",
      "justifyContent": "space-around",
      "alignItems": "center",
      "gap": 10,
      "backgroundColor": "#92a0ad",
      "borderRadius": 5,
      "borderColor": "#666666",
      "padding": 0,
      "shadowColor": "black",
      "shadowOffsetX": 1,
      "shadowOffsetY": 1,
      "shadowBlur": 3
    },
    "displayName": "Container",
    "custom": {},
    "parent": "navigationbarGridCell",
    "hidden": false,
    "nodes": [
      "navigationbarButton0",
      "navigationbarButton1",
      "navigationbarButton2",
      "navigationbarButton3"
    ],
    "linkedNodes": {}
  },
  "navigationbarButton0": {
    "type": { "resolvedName": "Button" },
    "isCanvas": false,
    "props": {
      "backgroundColor": "#778899",
      "fontSize": 14,
      "fontColor": "white",
      "borderRadius": 4,
      "width": 2.5,
      "height": 100,
      "text": "Home",
      "alignment": "center",
      "shadowColor": "black",
      "shadowOffsetX": 1,
      "shadowOffsetY": 1,
      "shadowBlur": 3
    },
    "displayName": "Button",
    "custom": {},
    "parent": "navigationbarContainer",
    "hidden": false,
    "nodes": [],
    "linkedNodes": {}
  },
  "navigationbarButton1": {
    "type": { "resolvedName": "Button" },
    "isCanvas": false,
    "props": {
      "backgroundColor": "#778899",
      "fontSize": 14,
      "fontColor": "white",
      "borderRadius": 4,
      "width": 2.5,
      "height": 100,
      "text": "NavItem1",
      "alignment": "center",
      "shadowColor": "black",
      "shadowOffsetX": 1,
      "shadowOffsetY": 1,
      "shadowBlur": 3
    },
    "displayName": "Button",
    "custom": {},
    "parent": "navigationbarContainer",
    "hidden": false,
    "nodes": [],
    "linkedNodes": {}
  },
  "navigationbarButton2": {
    "type": { "resolvedName": "Button" },
    "isCanvas": false,
    "props": {
      "backgroundColor": "#778899",
      "fontSize": 14,
      "fontColor": "white",
      "borderRadius": 4,
      "width": 2.5,
      "height": 100,
      "text": "NavItem2",
      "alignment": "center",
      "shadowColor": "black",
      "shadowOffsetX": 1,
      "shadowOffsetY": 1,
      "shadowBlur": 3
    },
    "displayName": "Button",
    "custom": {},
    "parent": "navigationbarContainer",
    "hidden": false,
    "nodes": [],
    "linkedNodes": {}
  },
  "navigationbarButton3": {
    "type": { "resolvedName": "Button" },
    "isCanvas": false,
    "props": {
      "backgroundColor": "#778899",
      "fontSize": 14,
      "fontColor": "white",
      "borderRadius": 4,
      "width": 2.5,
      "height": 100,
      "text": "NavItem3",
      "alignment": "center",
      "shadowColor": "black",
      "shadowOffsetX": 1,
      "shadowOffsetY": 1,
      "shadowBlur": 3
    },
    "displayName": "Button",
    "custom": {},
    "parent": "navigationbarContainer",
    "hidden": false,
    "nodes": [],
    "linkedNodes": {}
  },
  "leftsidebarGridCell": {
    "type": { "resolvedName": "GridCell" },
    "isCanvas": true,
    "props": {
      "flexDirection": "row",
      "justifyContent": "center",
      "alignItems": "center",
      "gap": 10
    },
    "displayName": "GridCell",
    "custom": { "id": "1" },
    "parent": "ROOT",
    "hidden": false,
    "nodes": ["leftsidebarContainer"],
    "linkedNodes": {}
  },
  "leftsidebarContainer": {
    "type": { "resolvedName": "Container" },
    "isCanvas": true,
    "props": {
      "height": 100,
      "width": 100,
      "flexDirection": "row",
      "justifyContent": "space-around",
      "alignItems": "center",
      "gap": 10,
      "backgroundColor": "#92a0ad",
      "borderRadius": 5,
      "borderColor": "#666666",
      "padding": 0,
      "shadowColor": "black",
      "shadowOffsetX": 1,
      "shadowOffsetY": 1,
      "shadowBlur": 3
    },
    "displayName": "Container",
    "custom": {},
    "parent": "leftsidebarGridCell",
    "hidden": false,
    "nodes": [
      "leftsidebarLabel0",
      "leftsidebarLabel1",
      "leftsidebarLabel2",
      "leftsidebarLabel3",
      "leftsidebarLabel4"
    ],
    "linkedNodes": {}
  },
  "leftsidebarLabel0": {
    "type": { "resolvedName": "Label" },
    "isCanvas": false,
    "props": {
      "text": "Menu Link 1",
      "fontSize": 22,
      "fontcolor": "black",
      "textAlign": "left",
      "bold": true,
      "italic": false,
      "underline": false
    },
    "displayName": "Label",
    "custom": {},
    "parent": "leftsidebarContainer",
    "hidden": false,
    "nodes": [],
    "linkedNodes": {}
  },
  "leftsidebarLabel1": {
    "type": { "resolvedName": "Label" },
    "isCanvas": false,
    "props": {
      "text": "Menu Link 2",
      "fontSize": 22,
      "fontcolor": "black",
      "textAlign": "left",
      "bold": true,
      "italic": false,
      "underline": false
    },
    "displayName": "Label",
    "custom": {},
    "parent": "leftsidebarContainer",
    "hidden": false,
    "nodes": [],
    "linkedNodes": {}
  },
  "leftsidebarLabel2": {
    "type": { "resolvedName": "Label" },
    "isCanvas": false,
    "props": {
      "text": "Menu Link 3",
      "fontSize": 22,
      "fontcolor": "black",
      "textAlign": "left",
      "bold": true,
      "italic": false,
      "underline": false
    },
    "displayName": "Label",
    "custom": {},
    "parent": "leftsidebarContainer",
    "hidden": false,
    "nodes": [],
    "linkedNodes": {}
  },
  "leftsidebarLabel3": {
    "type": { "resolvedName": "Label" },
    "isCanvas": false,
    "props": {
      "text": "Menu Link 4",
      "fontSize": 22,
      "fontcolor": "black",
      "textAlign": "left",
      "bold": true,
      "italic": false,
      "underline": false
    },
    "displayName": "Label",
    "custom": {},
    "parent": "leftsidebarContainer",
    "hidden": false,
    "nodes": [],
    "linkedNodes": {}
  },
  "leftsidebarLabel4": {
    "type": { "resolvedName": "Label" },
    "isCanvas": false,
    "props": {
      "text": "Menu Link 5",
      "fontSize": 22,
      "fontcolor": "black",
      "textAlign": "left",
      "bold": true,
      "italic": false,
      "underline": false
    },
    "displayName": "Label",
    "custom": {},
    "parent": "leftsidebarContainer",
    "hidden": false,
    "nodes": [],
    "linkedNodes": {}
  },
  "maincontentGridCell": {
    "type": { "resolvedName": "GridCell" },
    "isCanvas": true,
    "props": {
      "flexDirection": "row",
      "justifyContent": "center",
      "alignItems": "center",
      "gap": 10
    },
    "displayName": "GridCell",
    "custom": { "id": "2" },
    "parent": "ROOT",
    "hidden": false,
    "nodes": ["maincontentContainer"],
    "linkedNodes": {}
  },
  "maincontentContainer": {
    "type": { "resolvedName": "Container" },
    "isCanvas": true,
    "props": {
      "height": 100,
      "width": 100,
      "flexDirection": "row",
      "justifyContent": "space-around",
      "alignItems": "center",
      "gap": 10,
      "backgroundColor": "#92a0ad",
      "borderRadius": 5,
      "borderColor": "#666666",
      "padding": 0,
      "shadowColor": "black",
      "shadowOffsetX": 1,
      "shadowOffsetY": 1,
      "shadowBlur": 3
    },
    "displayName": "Container",
    "custom": {},
    "parent": "maincontentGridCell",
    "hidden": false,
    "nodes": ["maincontentText0", "maincontentImage1", "maincontentTextBox2", "maincontentText3"],
    "linkedNodes": {}
  },
  "maincontentText0": {
    "type": { "resolvedName": "Text" },
    "isCanvas": false,
    "props": {
      "text": "Step 1",
      "fontSize": 14,
      "fontColor": "black",
      "textAlign": "left",
      "bold": false,
      "italic": false,
      "underline": false,
      "userEditable": true
    },
    "displayName": "Text",
    "custom": {},
    "parent": "maincontentContainer",
    "hidden": false,
    "nodes": [],
    "linkedNodes": {}
  },
  "maincontentImage1": {
    "type": { "resolvedName": "Image" },
    "isCanvas": false,
    "props": {
      "src": "https://media.licdn.com/dms/image/D4E22AQGL4EZgEpG2ag/feedshare-shrink_800/0/17110080422738?e=2147483647&v=beta&t=Nj786KjutiTxei_wgDDM40hcWFi5_-qqBIKM4jOa3Hc",
      "alt": "To be replaced",
      "width": 100,
      "height": 60
    },
    "displayName": "Image",
    "custom": {},
    "parent": "maincontentContainer",
    "hidden": false,
    "nodes": [],
    "linkedNodes": {}
  },
  "maincontentTextBox2": {
    "type": { "resolvedName": "TextBox" },
    "isCanvas": false,
    "props": {
      "text": "Possible",
      "fontSize": 14,
      "fontColor": "black",
      "backgroundColor": "white",
      "placeholder": "Enter text",
      "borderRadius": 4,
      "height": 20,
      "width": 100,
      "alignment": "left"
    },
    "displayName": "TextBox",
    "custom": {},
    "parent": "maincontentContainer",
    "hidden": false,
    "nodes": [],
    "linkedNodes": {}
  },
  "maincontentText3": {
    "type": { "resolvedName": "Text" },
    "isCanvas": false,
    "props": {
      "text": "Additional Elements",
      "fontSize": 14,
      "fontColor": "black",
      "textAlign": "left",
      "bold": false,
      "italic": false,
      "underline": false,
      "userEditable": true
    },
    "displayName": "Text",
    "custom": {},
    "parent": "maincontentContainer",
    "hidden": false,
    "nodes": [],
    "linkedNodes": {}
  },
  "footerGridCell": {
    "type": { "resolvedName": "GridCell" },
    "isCanvas": true,
    "props": {
      "flexDirection": "row",
      "justifyContent": "center",
      "alignItems": "center",
      "gap": 10
    },
    "displayName": "GridCell",
    "custom": { "id": "3" },
    "parent": "ROOT",
    "hidden": false,
    "nodes": ["footerContainer"],
    "linkedNodes": {}
  },
  "footerContainer": {
    "type": { "resolvedName": "Container" },
    "isCanvas": true,
    "props": {
      "height": 100,
      "width": 100,
      "flexDirection": "row",
      "justifyContent": "space-around",
      "alignItems": "center",
      "gap": 10,
      "backgroundColor": "#92a0ad",
      "borderRadius": 5,
      "borderColor": "#666666",
      "padding": 0,
      "shadowColor": "black",
      "shadowOffsetX": 1,
      "shadowOffsetY": 1,
      "shadowBlur": 3
    },
    "displayName": "Container",
    "custom": {},
    "parent": "footerGridCell",
    "hidden": false,
    "nodes": ["footerInput0", "footerIcon1", "footerIcon2", "footerIcon3", "footerText4"],
    "linkedNodes": {}
  },
  "footerInput0": {
    "type": { "resolvedName": "Input" },
    "isCanvas": false,
    "props": {
      "fontSize": 14,
      "fontColor": "black",
      "backgroundColor": "white",
      "placeholder": "Search",
      "borderRadius": 4
    },
    "displayName": "Input",
    "custom": {},
    "parent": "footerContainer",
    "hidden": false,
    "nodes": [],
    "linkedNodes": {}
  },
  "footerIcon1": {
    "type": { "resolvedName": "Icon" },
    "isCanvas": false,
    "props": { "selectedIcon": "VscSearch", "iconSize": 24, "iconColor": "#778899" },
    "displayName": "Icon",
    "custom": {},
    "parent": "footerContainer",
    "hidden": false,
    "nodes": [],
    "linkedNodes": {}
  },
  "footerIcon2": {
    "type": { "resolvedName": "Icon" },
    "isCanvas": false,
    "props": { "selectedIcon": "VscHome", "iconSize": 24, "iconColor": "#778899" },
    "displayName": "Icon",
    "custom": {},
    "parent": "footerContainer",
    "hidden": false,
    "nodes": [],
    "linkedNodes": {}
  },
  "footerIcon3": {
    "type": { "resolvedName": "Icon" },
    "isCanvas": false,
    "props": { "selectedIcon": "VscInfo", "iconSize": 24, "iconColor": "#778899" },
    "displayName": "Icon",
    "custom": {},
    "parent": "footerContainer",
    "hidden": false,
    "nodes": [],
    "linkedNodes": {}
  },
  "footerText4": {
    "type": { "resolvedName": "Text" },
    "isCanvas": false,
    "props": {
      "text": "Contact Info",
      "fontSize": 14,
      "fontColor": "black",
      "textAlign": "left",
      "bold": false,
      "italic": false,
      "underline": false,
      "userEditable": true
    },
    "displayName": "Text",
    "custom": {},
    "parent": "footerContainer",
    "hidden": false,
    "nodes": [],
    "linkedNodes": {}
  }
}
