{"ROOT":{"type":{"resolvedName":"Container"},"isCanvas":true,"props":{"id":"root"},"displayName":"Container","custom":{},"hidden":false,"nodes":["DekgVT2Xxt"],"linkedNodes":{}},"DekgVT2Xxt":{"type":{"resolvedName":"Rows"},"isCanvas":false,"props":{"numberOfRows":2,"gap":0},"displayName":"Rows","custom":{},"parent":"ROOT","hidden":false,"nodes":[],"linkedNodes":{"row-0":"-PQE-71Ffq","row-1":"9BRVN5lZTT"}},"-PQE-71Ffq":{"type":{"resolvedName":"Row"},"isCanvas":true,"props":{},"displayName":"Row","custom":{},"parent":"DekgVT2Xxt","hidden":false,"nodes":["-9v5H5rUTM"],"linkedNodes":{}},"9BRVN5lZTT":{"type":{"resolvedName":"Row"},"isCanvas":true,"props":{},"displayName":"Row","custom":{},"parent":"DekgVT2Xxt","hidden":false,"nodes":[],"linkedNodes":{}},"-9v5H5rUTM":{"type":{"resolvedName":"Columns"},"isCanvas":false,"props":{"numberOfCols":2,"gap":0},"displayName":"Columns","custom":{},"parent":"-PQE-71Ffq","hidden":false,"nodes":[],"linkedNodes":{"column-0":"HnP1kug19z","column-1":"DStQkO4IY_"}},"HnP1kug19z":{"type":{"resolvedName":"Column"},"isCanvas":true,"props":{"style":{"gridColumn":"span 5"}},"displayName":"Column","custom":{},"parent":"-9v5H5rUTM","hidden":false,"nodes":[],"linkedNodes":{}},"DStQkO4IY_":{"type":{"resolvedName":"Column"},"isCanvas":true,"props":{"style":{"gridColumn":"span 5"}},"displayName":"Column","custom":{},"parent":"-9v5H5rUTM","hidden":false,"nodes":[],"linkedNodes":{}}}